test_pack/__init__.py
test_pack/core/__init__.py
test_pack/core/coree.py
test_pack/utils/__init__.py
test_pack/utils/utilss.py
packtest1-0.0.1.dist-info/LICENSE
packtest1-0.0.1.dist-info/METADATA
packtest1-0.0.1.dist-info/WHEEL
packtest1-0.0.1.dist-info/top_level.txt
packtest1-0.0.1.dist-info/RECORD
