Metadata-Version: 2.1
Name: packtest1
Version: 0.0.1
Summary: A package for converting between imperial unit lengths and weights.
Author: All credit to you
Author-email: you@chapter4.com
License: MIT license
Keywords: test pack
Classifier: Development Status :: 2 - Pre-Alpha
Classifier: Intended Audience :: Developers
Classifier: License :: OSI Approved :: MIT License
Classifier: Natural Language :: English
Classifier: Programming Language :: Python :: 3
Classifier: Programming Language :: Python :: 3.6
License-File: LICENSE
Requires-Dist: numpy >=1.10
Requires-Dist: pandas
